rpoems/__init__.py
rpoems/main.py
rpoems/redditpg.py
rpoems-1.0.2.dist-info/LICENSE
rpoems-1.0.2.dist-info/METADATA
rpoems-1.0.2.dist-info/WHEEL
rpoems-1.0.2.dist-info/top_level.txt
rpoems-1.0.2.dist-info/RECORD
