Metadata-Version: 2.1
Name: rpoems
Version: 1.0.2
Summary: Generate poems with comments from Reddit
Home-page: https://github.com/Acryptarch/Reddit-Poem-Generator
Author: Neeraj Mula
Author-email: neeraj.mula@rutgers.edu
License: UNKNOWN
Platform: UNKNOWN
Classifier: Programming Language :: Python :: 3
Classifier: License :: OSI Approved :: MIT License
Classifier: Operating System :: OS Independent
Requires-Python: >=3.6
Requires-Dist: pronouncing
Requires-Dist: psaw
